setup.py
dsnd_lz_distributions/Binomialdistribution.py
dsnd_lz_distributions/Gaussiandistribution.py
dsnd_lz_distributions/Generaldistribution.py
dsnd_lz_distributions/__init__.py
dsnd_lz_distributions.egg-info/PKG-INFO
dsnd_lz_distributions.egg-info/SOURCES.txt
dsnd_lz_distributions.egg-info/dependency_links.txt
dsnd_lz_distributions.egg-info/not-zip-safe
dsnd_lz_distributions.egg-info/top_level.txt