Metadata-Version: 1.0
Name: dsnd-lz-distributions
Version: 0.1
Summary: Gaussian and Binomial distributions
Home-page: UNKNOWN
Author: Liankun Zou
Author-email: zz.guku@gmail.com
License: UNKNOWN
Platform: UNKNOWN
